generate_wisdom.py
generate_wisdom-0.0.3.dist-info/METADATA
generate_wisdom-0.0.3.dist-info/WHEEL
generate_wisdom-0.0.3.dist-info/top_level.txt
generate_wisdom-0.0.3.dist-info/RECORD
