Metadata-Version: 2.1
Name: generate-wisdom
Version: 0.0.3
Summary: Makes random wise-sounding sayings
Home-page: UNKNOWN
License: UNKNOWN
Platform: UNKNOWN
Classifier: Programming Language :: Python :: 3
